{
    "version": 1,
    "revision": 0,
    "rules": [
        {
            "primary-output": "E:\\codes\\openGL\\VkSamples_OGL\\Components\\int\\nocopyable.h.obj",
            "outputs": [
                "E:\\codes\\openGL\\VkSamples_OGL\\Components\\bin\\Components.pdb",
                "E:\\codes\\openGL\\VkSamples_OGL\\Components\\int\\",
                "E:\\codes\\openGL\\VkSamples_OGL\\Components\\int\\nocopyable.h.ifc"
            ],
            "provides": [
                {
                    "logical-name": "nocopyable.h",
                    "source-path": "e:\\codes\\opengl\\vksamples_ogl\\components\\nocopyable.h",
                    "lookup-method": "absolute"
                }
            ],
            "requires": []
        }
    ]
}